<?xml version="1.0" ?>
<song xmlns="http://openlyrics.info/namespace/2009/song" version="0.8" createdIn="OpenLP 2.4.6" modifiedIn="OpenLP 2.4.6" modifiedDate="2021-06-12T03:38:19">
   <properties>
      <titles>
         <title>Bhajan176 Hey Mero Praan Uthasanga</title>
      </titles>
      <authors>
         <author>Nepali Christain Bhajan</author>
      </authors>
      <songbooks>
         <songbook name="bhajan" entry="1"/>
      </songbooks>
      <verseOrder>v1 v2 v3 v4 </verseOrder>
   </properties>
   <lyrics>
      <verse name="v1">
         <lines>
            १. हे मेरो प्राण, उठ्सँग घाम र पूरो गर् सब आफ्नो काम
            <br/>
            अल्छेई छोड् र स्तुति गा, बिहानको प्रार्थना चढा । 
         </lines>
      </verse>
      <verse name="v2">
         <lines>
             २. बिता यो दिन भई बुद्धिमान, सबै दिनलाई त अन्तकै ठान्
            <br/>
            ईश्वरको दानको गर् विचार, नियाको लागि रह तयार । 
         </lines>
      </verse>
      <verse name="v3">
         <lines>
             ३. हे ईश्वर, गर्छु प्रार्थना यो, जेजे गरूँला आज म
            <br/>
            ती सबमा मलाई गोहार देऊ, मनमा पवित्र आत्मा देऊ । 
         </lines>
      </verse>
      <verse name="v4">
         <lines>
             ४. अँ आज मेरो बाटोले आफ्नो महिमा बढाइदेऊ
            <br/>
            अँ पिता, पुत्र, आत्मामा सधैँका परम महिमा ।
         </lines>
      </verse>
   </lyrics>
</song>
