<?xml version="1.0" ?>
<song xmlns="http://openlyrics.info/namespace/2009/song" version="0.8" createdIn="OpenLP 2.4.6" modifiedIn="OpenLP 2.4.6" modifiedDate="2021-06-12T03:38:19">
   <properties>
      <titles>
         <title>Bhajan589 Prabhu Yeshuko Janma Bhayo</title>
      </titles>
      <authors>
         <author>Nepali Christain Bhajan</author>
      </authors>
      <songbooks>
         <songbook name="bhajan" entry="1"/>
      </songbooks>
      <verseOrder>c1 v1 c1 v2 c1 v3 c1 </verseOrder>
   </properties>
   <lyrics>
      <verse name="c1">
         <lines>
            कोः प्रभु येशूको जन्म भयो गाईको गोठैमा,
            <br/>
            पापीलाई भनी आए प्रभु मान्छेको चोलामा (२)
            <br/>
            ज्योतिषीहरू अघि बढे तारालाई हेरेर
            <br/>
            दर्शन गरी, चढाए भेटी दण्डवत् गरेर । 
         </lines>
      </verse>
      <verse name="v1">
         <lines>
             १. अचम्मित भए गोठालाहरू स्वर्गदूतलाई देखेर
            <br/>
            खबर दिन गए सबै नै साह्रै नै खुसी भएर २
            <br/>
            पिताको आज्ञा पूरा गर्न आउनुभयो येशू संसारमा (२) 
         </lines>
      </verse>
      <verse name="v2">
         <lines>
             २. हामीलाई पुत्र दिनुभयो स्वर्गका पिता परमेश्वरले
            <br/>
            पापको बोझ उठाउन जन्म लिनुभयो येशूले २ 
         </lines>
      </verse>
      <verse name="v3">
         <lines>
             ३. आउनुभयो येशू हामी सबैलाई मुक्तिको बाटो देखाउन
            <br/>
            जन्मे गोठमा सबैलाई साँचो (परमेश्वर चिनाउन) २
         </lines>
      </verse>
   </lyrics>
</song>
