<?xml version="1.0" ?>
<song xmlns="http://openlyrics.info/namespace/2009/song" version="0.8" createdIn="OpenLP 2.4.6" modifiedIn="OpenLP 2.4.6" modifiedDate="2021-06-12T03:38:19">
   <properties>
      <titles>
         <title>Bhajan145 Pabitra Aatma Aguwa</title>
      </titles>
      <authors>
         <author>Nepali Christain Bhajan</author>
      </authors>
      <songbooks>
         <songbook name="bhajan" entry="1"/>
      </songbooks>
      <verseOrder>v1 v2 v3 </verseOrder>
   </properties>
   <lyrics>
      <verse name="v1">
         <lines>
            १. पवित्र आत्मा अगुवा सधैं बस्नुहोस् साथमा
            <br/>
            यहाँ पर्देशी जो छु लौ डोर्‌याउनुहोस् प्रभु
            <br/>
            थकित प्राण रमाउनेछ स्वर तपाईंको सुनेर
            <br/>
            यसो भन्दै गरेको आइज तँलाई डोर्‌याउँछु । 
         </lines>
      </verse>
      <verse name="v2">
         <lines>
             २. साथमा बस्नुहोस् सधैं गोहार दिइरहने तपाईं
            <br/>
            अन्धकारको माझमै प्रभु नछोड्नोस् मलाई
            <br/>
            जब आँधी चल्दछ, जब सानो हुन्छ मन
            <br/>
            भन्नुहवस् बिस्तारै आइज डोर्‌याउँछु तँलाई । 
         </lines>
      </verse>
      <verse name="v3">
         <lines>
             ३. मेरो बेला आइपुग्दा जान तपाईंछेउ वहाँ
            <br/>
            जब स्वर्गलाई सम्झन्छु आशा गर्दै इनामको
            <br/>
            बसीकन यो ठाउँमै हेर्छु जब तपाईंलाई
            <br/>
            भन्नुहवस् बिस्तारै आइज डोर्‌याउँछु तँलाई ।
         </lines>
      </verse>
   </lyrics>
</song>
